README.md
setup.py
coap_core/__init__.py
coap_core/coap_packet/__init__.py
coap_core/coap_packet/coap_config.py
coap_core/coap_packet/coap_packet.py
coap_core/coap_packet/coap_templates.py
coap_core/coap_resource/__init__.py
coap_core/coap_resource/resource.py
coap_core/coap_resource/resource_manager.py
coap_core/coap_transaction/__init__.py
coap_core/coap_transaction/coap_transaction.py
coap_core/coap_transaction/coap_transaction_pool.py
coap_core/coap_utilities/__init__.py
coap_core/coap_utilities/coap_logger.py
coap_core/coap_utilities/coap_singleton.py
coap_core/coap_utilities/coap_timer.py
coap_core/coap_worker/__init__.py
coap_core/coap_worker/coap_worker.py
coap_core/coap_worker/coap_worker_pool.py
share_drive/__init__.py
share_drive.egg-info/PKG-INFO
share_drive.egg-info/SOURCES.txt
share_drive.egg-info/dependency_links.txt
share_drive.egg-info/entry_points.txt
share_drive.egg-info/not-zip-safe
share_drive.egg-info/requires.txt
share_drive.egg-info/top_level.txt
share_drive/share_drive_client/__init__.py
share_drive/share_drive_client/client.py
share_drive/share_drive_client/client_resource.py
share_drive/share_drive_helpers/__init__.py
share_drive/share_drive_helpers/drive_assembler.py
share_drive/share_drive_helpers/drive_spliter.py
share_drive/share_drive_helpers/drive_templates.py
share_drive/share_drive_helpers/drive_utils.py
share_drive/share_drive_server/__init__.py
share_drive/share_drive_server/server.py
share_drive/share_drive_server/server_resource.py